LICENSE.txt
MANIFEST.in
README.md
setup.cfg
setup.py
dblogging/__init__.py
dblogging/config.py
dblogging/logger.py
dblogging.egg-info/PKG-INFO
dblogging.egg-info/SOURCES.txt
dblogging.egg-info/dependency_links.txt
dblogging.egg-info/requires.txt
dblogging.egg-info/top_level.txt
dblogging/generators/__init__.py
dblogging/generators/html_gen/__init__.py
dblogging/generators/html_gen/html_generator.py
dblogging/sqlite/__init__.py
dblogging/sqlite/dal.py
examples/logs/actions.js
examples/logs/python.css
examples/logs/styles.css